mistletoe/__init__.py
mistletoe/_html.py
mistletoe/attr_doc.py
mistletoe/base_elements.py
mistletoe/block_tokenizer.py
mistletoe/block_tokens.py
mistletoe/block_tokens_ext.py
mistletoe/nested_tokenizer.py
mistletoe/parse_context.py
mistletoe/span_tokenizer.py
mistletoe/span_tokens.py
mistletoe/span_tokens_ext.py
mistletoe/token_sets.py
mistletoe/cli/__init__.py
mistletoe/cli/benchmark.py
mistletoe/cli/parse.py
mistletoe/renderers/__init__.py
mistletoe/renderers/base.py
mistletoe/renderers/html.py
mistletoe/renderers/json.py
mistletoe/renderers/latex.py
test/__init__.py
test/test_base_elements.py
test/test_block_token.py
test/test_cli.py
test/test_footnotes.py
test/test_nested_tokenizer.py
test/test_span_token.py
test/commonmark/__init__.py
test/commonmark/__main__.py
test/commonmark/commonmark.py
test/commonmark/test_commonmark.py
test/test_contrib/__init__.py
test/test_contrib/test_github_wiki.py
test/test_contrib/test_jira_renderer.py
test/test_contrib/test_mathjax.py
test/test_contrib/test_scheme.py
test/test_contrib/test_toc_renderer.py
test/test_samples/__init__.py
test/test_samples/mprofile.py
test/test_samples/test_samples.py
mistletoe_ebp-0.10.0.dist-info/LICENSE
mistletoe_ebp-0.10.0.dist-info/METADATA
mistletoe_ebp-0.10.0.dist-info/WHEEL
mistletoe_ebp-0.10.0.dist-info/entry_points.txt
mistletoe_ebp-0.10.0.dist-info/top_level.txt
mistletoe_ebp-0.10.0.dist-info/RECORD
