Metadata-Version: 2.1
Name: mistletoe-ebp
Version: 0.10.0
Summary: A fast, extensible Markdown parser in pure Python.
Home-page: https://github.com/ExecutableBookProject/mistletoe-ebp
Author: Chris Sewell
Author-email: chrisj_sewell@hotmail.com
License: MIT
Project-URL: Documentation, https://mistletoe-ebp.readthedocs.io
Keywords: markdown lexer parser development
Platform: UNKNOWN
Classifier: Development Status :: 3 - Alpha
Classifier: Intended Audience :: Developers
Classifier: License :: OSI Approved :: MIT License
Classifier: Programming Language :: Python :: 3
Classifier: Programming Language :: Python :: 3.3
Classifier: Programming Language :: Python :: 3.4
Classifier: Programming Language :: Python :: 3.5
Classifier: Programming Language :: Python :: 3.6
Classifier: Programming Language :: Python :: Implementation :: CPython
Classifier: Programming Language :: Python :: Implementation :: PyPy
Classifier: Topic :: Software Development :: Libraries :: Python Modules
Classifier: Topic :: Text Processing :: Markup
Requires-Python: ~=3.6
Requires-Dist: attrs (~=19.3)
Provides-Extra: benchmark
Requires-Dist: commonmark (~=0.9.1) ; extra == 'benchmark'
Requires-Dist: markdown (~=3.2) ; extra == 'benchmark'
Requires-Dist: mistune (~=0.8.4) ; extra == 'benchmark'
Requires-Dist: panflute (~=1.12) ; extra == 'benchmark'
Provides-Extra: code_style
Requires-Dist: flake8 (<3.8.0,>=3.7.0) ; extra == 'code_style'
Requires-Dist: black (==19.10b0) ; extra == 'code_style'
Requires-Dist: pre-commit (==1.17.0) ; extra == 'code_style'
Provides-Extra: rtd
Requires-Dist: sphinx (<3,>=2) ; extra == 'rtd'
Requires-Dist: myst-parser (~=0.6.0a3) ; extra == 'rtd'
Requires-Dist: pyyaml ; extra == 'rtd'
Provides-Extra: testing
Requires-Dist: coverage ; extra == 'testing'
Requires-Dist: pytest (<4,>=3.6) ; extra == 'testing'
Requires-Dist: pytest-cov ; extra == 'testing'
Requires-Dist: pytest-regressions ; extra == 'testing'
